README.md
README_PYPI.md
phylodeep/__init__.py
phylodeep/checkdeep.py
phylodeep/ci_comput.py
phylodeep/encoding.py
phylodeep/model_load.py
phylodeep/modeldeep.py
phylodeep/paramdeep.py
phylodeep/reformat_models.py
phylodeep/sumstats.py
phylodeep/tree_utilities.py
phylodeep/pca_a_priori/models/BDEI_LARGE_PCA.pkl
phylodeep/pca_a_priori/models/BDEI_SMALL_PCA.pkl
phylodeep/pca_a_priori/models/BDSS_LARGE_PCA.pkl
phylodeep/pca_a_priori/models/BD_LARGE_PCA.pkl
phylodeep/pca_a_priori/models/BD_SMALL_PCA.pkl
phylodeep/pca_a_priori/scalers/BDEI_LARGE_PCA.pkl
phylodeep/pca_a_priori/scalers/BDEI_SMALL_PCA.pkl
phylodeep/pca_a_priori/scalers/BDSS_LARGE_PCA.pkl
phylodeep/pca_a_priori/scalers/BD_LARGE_PCA.pkl
phylodeep/pca_a_priori/scalers/BD_SMALL_PCA.pkl
phylodeep/pca_a_priori/simulated_data/BDEI_LARGE_PCA.csv
phylodeep/pca_a_priori/simulated_data/BDEI_SMALL_PCA.csv
phylodeep/pca_a_priori/simulated_data/BDSS_LARGE_PCA.csv
phylodeep/pca_a_priori/simulated_data/BD_LARGE_PCA.csv
phylodeep/pca_a_priori/simulated_data/BD_SMALL_PCA.csv
phylodeep/pretrained_models/models/BDEI_LARGE_CNN.h5
phylodeep/pretrained_models/models/BDEI_LARGE_FFNN.h5
phylodeep/pretrained_models/models/BDEI_SMALL_CNN.h5
phylodeep/pretrained_models/models/BDEI_SMALL_FFNN.h5
phylodeep/pretrained_models/models/BDSS_LARGE_CNN.h5
phylodeep/pretrained_models/models/BDSS_LARGE_FFNN.h5
phylodeep/pretrained_models/models/BD_LARGE_CNN.h5
phylodeep/pretrained_models/models/BD_LARGE_FFNN.h5
phylodeep/pretrained_models/models/BD_SMALL_CNN.h5
phylodeep/pretrained_models/models/BD_SMALL_FFNN.h5
phylodeep/pretrained_models/models/BD_vs_BDEI_SMALL_CNN.h5
phylodeep/pretrained_models/models/BD_vs_BDEI_SMALL_FFNN.h5
phylodeep/pretrained_models/models/BD_vs_BDEI_vs_BDSS_LARGE_CNN.h5
phylodeep/pretrained_models/models/BD_vs_BDEI_vs_BDSS_LARGE_FFNN.h5
phylodeep/pretrained_models/scalers/BDEI_LARGE_FFNN.pkl
phylodeep/pretrained_models/scalers/BDEI_SMALL_FFNN.pkl
phylodeep/pretrained_models/scalers/BDSS_LARGE_FFNN.pkl
phylodeep-0.9.dist-info/LICENSE
phylodeep-0.9.dist-info/METADATA
phylodeep-0.9.dist-info/WHEEL
phylodeep-0.9.dist-info/entry_points.txt
phylodeep-0.9.dist-info/top_level.txt
phylodeep-0.9.dist-info/RECORD
