Metadata-Version: 2.1
Name: phylodeep
Version: 0.9
Summary: Phylodynamic paramater and model inference using pretrained deep neural networks.
Home-page: https://github.com/evolbioinfo/phylodeep
Author: Jakub Voznica
Author-email: jakub.voznica@pasteur.fr
Maintainer: Anna Zhukova
Maintainer-email: anna.zhukova@pasteur.fr
Keywords: phylodynamics,molecular epidemiology,phylogeny,model selection,paramdeep,phylodeep,deep learning,convolutional networks
Classifier: Development Status :: 4 - Beta
Classifier: Environment :: Console
Classifier: Intended Audience :: Science/Research
Classifier: Topic :: Scientific/Engineering :: Artificial Intelligence
Classifier: Topic :: Scientific/Engineering :: Bio-Informatics
Classifier: Topic :: Software Development :: Libraries :: Python Modules
Classifier: Programming Language :: Python :: 3
Classifier: Programming Language :: Python :: 3.8
Classifier: Programming Language :: Python :: 3.9
Classifier: Programming Language :: Python :: 3 :: Only
Requires-Python: >=3.8
License-File: LICENSE
Requires-Dist: scikit-learn==1.5.2
Requires-Dist: tensorflow==2.17.0
Requires-Dist: ete3==3.1.3
Requires-Dist: matplotlib==3.9.2
Requires-Dist: keras==3.5.0
Requires-Dist: phylodeep-data-bd>=0.6
Requires-Dist: phylodeep-data-bdei>=0.4
Requires-Dist: phylodeep-data-bdss>=0.4
